{
    "_id": "em3glccrJ5ZIf8Uq",
    "img": "systems/pf2e/icons/default-icons/feats.webp",
    "name": "Keep Pace (Game Hunter)",
    "system": {
        "actionType": {
            "value": "reaction"
        },
        "actions": {
            "value": null
        },
        "category": "class",
        "description": {
            "value": "<p>When your hunted prey tries to bolt, you follow. You Stride up to your Speed, following your hunted prey and keeping it in reach throughout its movement until it stops moving or you've moved your full Speed.</p>\n<p>You can use Keep Pace to @UUID[Compendium.pf2e.actionspf2e.Item.Burrow], @UUID[Compendium.pf2e.actionspf2e.Item.Climb], @UUID[Compendium.pf2e.actionspf2e.Item.Fly], or @UUID[Compendium.pf2e.actionspf2e.Item.Swim] instead of Stride if you have the appropriate movement type.</p>"
        },
        "level": {
            "value": 6
        },
        "prerequisites": {
            "value": [
                {
                    "value": "Game Hunter Dedication"
                }
            ]
        },
        "rules": [],
        "source": {
            "value": "Pathfinder #175: Broken Tusk Moon"
        },
        "traits": {
            "rarity": "common",
            "value": [
                "archetype"
            ]
        }
    },
    "type": "feat"
}
