{
    "_id": "HqN4nUnl75foBKLZ",
    "data": {
        "abilities": {
            "cha": {
                "mod": 5
            },
            "con": {
                "mod": 2
            },
            "dex": {
                "mod": 4
            },
            "int": {
                "mod": 7
            },
            "str": {
                "mod": 1
            },
            "wis": {
                "mod": 3
            }
        },
        "attributes": {
            "ac": {
                "details": "",
                "value": 44
            },
            "allSaves": {
                "value": ""
            },
            "hp": {
                "details": "",
                "max": 375,
                "temp": 0,
                "value": 375
            },
            "initiative": {
                "ability": "perception"
            },
            "perception": {
                "value": 36
            },
            "shield": {
                "ac": 0,
                "brokenThreshold": 0,
                "hardness": 0,
                "max": 0,
                "value": 0
            },
            "speed": {
                "otherSpeeds": [],
                "value": "25"
            }
        },
        "details": {
            "alignment": {
                "value": "LN"
            },
            "creatureType": "",
            "level": {
                "value": 20
            },
            "source": {
                "value": "Pathfinder #166: Despair on Danger Island"
            }
        },
        "resources": {},
        "saves": {
            "fortitude": {
                "saveDetail": "",
                "value": 32
            },
            "reflex": {
                "saveDetail": "",
                "value": 34
            },
            "will": {
                "saveDetail": "",
                "value": 33
            }
        },
        "traits": {
            "attitude": {
                "value": "hostile"
            },
            "ci": [],
            "di": {
                "custom": "",
                "value": []
            },
            "dr": [],
            "dv": [],
            "languages": {
                "custom": "",
                "selected": [],
                "value": [
                    "celestial",
                    "elven",
                    "sylvan",
                    "taldane",
                    "tengu",
                    "tien"
                ]
            },
            "rarity": {
                "value": "unique"
            },
            "senses": {
                "value": ""
            },
            "size": {
                "value": "med"
            },
            "traits": {
                "custom": "",
                "value": [
                    "human",
                    "humanoid"
                ]
            }
        }
    },
    "effects": [],
    "flags": {},
    "img": "systems/pf2e/icons/default-icons/npc.svg",
    "items": [
        {
            "_id": "f0QSYj6HRyqRWrz2",
            "data": {
                "MAP": {
                    "value": ""
                },
                "ability": {
                    "value": "str"
                },
                "baseItem": null,
                "bonus": {
                    "value": 0
                },
                "bonusDamage": {
                    "value": 0
                },
                "brokenThreshold": {
                    "value": 0
                },
                "bulkCapacity": {
                    "value": ""
                },
                "collapsed": {
                    "value": false
                },
                "containerId": {
                    "value": null
                },
                "damage": {
                    "damageType": "slashing",
                    "dice": 1,
                    "die": "d4",
                    "value": ""
                },
                "description": {
                    "value": "<p>This short, single-edged sword typically features a cross guard that helps catch oncoming attacks. It is the preferred weapon of Butterfly Blades-highly skilled Gokan assassins.</p>"
                },
                "equipped": {
                    "value": false
                },
                "equippedBulk": {
                    "value": ""
                },
                "group": {
                    "value": "sword"
                },
                "hands": {
                    "value": false
                },
                "hardness": {
                    "value": 0
                },
                "hp": {
                    "value": 0
                },
                "identification": {
                    "misidentified": {},
                    "status": "identified",
                    "unidentified": {
                        "data": {
                            "description": {
                                "value": ""
                            }
                        },
                        "img": "",
                        "name": ""
                    }
                },
                "invested": {
                    "value": null
                },
                "level": {
                    "value": 0
                },
                "maxHp": {
                    "value": 0
                },
                "negateBulk": {
                    "value": "0"
                },
                "potencyRune": {
                    "value": null
                },
                "preciousMaterial": {
                    "value": null
                },
                "preciousMaterialGrade": {
                    "value": null
                },
                "price": {
                    "value": "0 gp"
                },
                "property1": {
                    "critDamage": "",
                    "critDamageType": "",
                    "critDice": 0,
                    "critDie": "",
                    "criticalConditionType": "",
                    "criticalConditionValue": null,
                    "damageType": "",
                    "dice": 0,
                    "die": "",
                    "strikeConditionType": "",
                    "strikeConditionValue": null,
                    "value": ""
                },
                "propertyRune1": {
                    "value": null
                },
                "propertyRune2": {
                    "value": null
                },
                "propertyRune3": {
                    "value": null
                },
                "propertyRune4": {
                    "value": null
                },
                "quantity": {
                    "value": 1
                },
                "range": {
                    "value": "melee"
                },
                "reload": {
                    "value": ""
                },
                "rules": [],
                "size": {
                    "value": "med"
                },
                "slug": "butterfly-sword",
                "source": {
                    "value": ""
                },
                "specific": {
                    "value": false
                },
                "splashDamage": {
                    "value": 0
                },
                "stackGroup": {
                    "value": ""
                },
                "strikingRune": {
                    "value": ""
                },
                "traits": {
                    "custom": "",
                    "rarity": {
                        "value": "common"
                    },
                    "value": [
                        "agile",
                        "disarm",
                        "finesse",
                        "monk",
                        "parry",
                        "twin"
                    ]
                },
                "usage": {
                    "value": "held-in-one-hand"
                },
                "weaponType": {
                    "value": "advanced"
                },
                "weight": {
                    "value": "L"
                }
            },
            "effects": [],
            "flags": {
                "core": {
                    "sourceId": "Compendium.pf2e.equipment-srd.JuR0cug2xq4sWxHR"
                }
            },
            "img": "systems/pf2e/icons/default-icons/weapon.svg",
            "name": "Butterfly Sword",
            "sort": 100000,
            "type": "weapon"
        },
        {
            "_id": "YdVEiekS8A4oqtsT",
            "data": {
                "armor": {
                    "value": 0
                },
                "armorType": {
                    "value": "unarmored"
                },
                "baseItem": null,
                "brokenThreshold": {
                    "value": null
                },
                "bulkCapacity": {
                    "value": ""
                },
                "check": {
                    "value": 0
                },
                "collapsed": {
                    "value": false
                },
                "containerId": {
                    "value": ""
                },
                "description": {
                    "value": "<p>Explorer's clothing is sturdy enough that it can be reinforced to protect you, even though it isn't a suit of armor. It comes in many forms, though the most common sorts look like clerical vestments, monk's garments, or wizard's robes, as members of all three classes are likely to avoid wearing armor.</p>"
                },
                "dex": {
                    "value": 5
                },
                "equipped": {
                    "value": false
                },
                "equippedBulk": {
                    "value": "L"
                },
                "group": {
                    "value": null
                },
                "hardness": {
                    "value": null
                },
                "hp": {
                    "value": null
                },
                "identification": {
                    "misidentified": {},
                    "status": "identified",
                    "unidentified": {
                        "data": {
                            "description": {
                                "value": ""
                            }
                        },
                        "img": "",
                        "name": ""
                    }
                },
                "invested": {
                    "value": false
                },
                "level": {
                    "value": 14
                },
                "maxHp": {
                    "value": null
                },
                "negateBulk": {
                    "value": "0"
                },
                "potencyRune": {
                    "value": 2
                },
                "preciousMaterial": {
                    "value": null
                },
                "preciousMaterialGrade": {
                    "value": null
                },
                "price": {
                    "value": "4500 gp"
                },
                "propertyRune1": {
                    "value": ""
                },
                "propertyRune2": {
                    "value": ""
                },
                "propertyRune3": {
                    "value": ""
                },
                "propertyRune4": {
                    "value": ""
                },
                "quantity": {
                    "value": 1
                },
                "resiliencyRune": {
                    "value": "greaterResilient"
                },
                "rules": [],
                "size": {
                    "value": "med"
                },
                "slug": "clothing-explorers",
                "source": {
                    "value": ""
                },
                "speed": {
                    "value": 0
                },
                "stackGroup": {
                    "value": ""
                },
                "strength": {
                    "value": 0
                },
                "traits": {
                    "custom": "",
                    "rarity": {
                        "value": "common"
                    },
                    "value": []
                },
                "usage": {
                    "value": "wornarmor"
                },
                "weight": {
                    "value": "1"
                }
            },
            "effects": [],
            "flags": {
                "core": {
                    "sourceId": "Compendium.pf2e.equipment-srd.dDIPA1WE9ESF67EB"
                }
            },
            "img": "systems/pf2e/icons/equipment/adventuring-gear/clothes-explorers.webp",
            "name": "+2 Greater Resilient Aristocrat’s Clothing",
            "sort": 200000,
            "type": "armor"
        },
        {
            "_id": "8AuQ37IrQ8nabrt2",
            "data": {
                "baseItem": null,
                "brokenThreshold": {
                    "value": 0
                },
                "bulkCapacity": {
                    "value": ""
                },
                "collapsed": {
                    "value": false
                },
                "containerId": {
                    "value": ""
                },
                "description": {
                    "value": "<p>This ordinary-looking hat allows you to cloak yourself in illusions.</p>\n<p><strong>Activate</strong> <span class=\"pf2-icon\">D</span> Interact</p>\n<p><strong>Frequency</strong> any number of times per day</p>\n<p><strong>Effect</strong> The hat casts a 2nd-level @Compendium[pf2e.spells-srd.Illusory Disguise]{Illusory Disguise} spell on you. While setting up the disguise, you can magically alter the hat to appear as a comb, ribbon, helm, or other piece of headwear.</p>"
                },
                "equipped": {
                    "value": false
                },
                "equippedBulk": {
                    "value": ""
                },
                "hardness": {
                    "value": 0
                },
                "hp": {
                    "value": 0
                },
                "identification": {
                    "misidentified": {},
                    "status": "identified",
                    "unidentified": {
                        "data": {
                            "description": {
                                "value": ""
                            }
                        },
                        "img": "",
                        "name": ""
                    }
                },
                "invested": {
                    "value": false
                },
                "level": {
                    "value": 7
                },
                "maxHp": {
                    "value": 0
                },
                "negateBulk": {
                    "value": "0"
                },
                "preciousMaterial": {
                    "value": ""
                },
                "preciousMaterialGrade": {
                    "value": ""
                },
                "price": {
                    "value": "340 gp"
                },
                "quantity": {
                    "value": 1
                },
                "rules": [],
                "size": {
                    "value": "med"
                },
                "slug": "hat-of-disguise-greater",
                "source": {
                    "value": ""
                },
                "stackGroup": {
                    "value": ""
                },
                "traits": {
                    "custom": "",
                    "rarity": {
                        "value": "common"
                    },
                    "value": [
                        "illusion",
                        "invested",
                        "magical"
                    ]
                },
                "usage": {
                    "value": "wornheadwear"
                },
                "weight": {
                    "value": "-"
                }
            },
            "effects": [],
            "flags": {
                "core": {
                    "sourceId": "Compendium.pf2e.equipment-srd.WPSp5MLb0VOfmUqH"
                }
            },
            "img": "systems/pf2e/icons/equipment/worn-items/other-worn-items/hat-of-disguise.webp",
            "name": "Hat of Disguise (Greater)",
            "sort": 300000,
            "type": "equipment"
        },
        {
            "_id": "jbXgp798w9mkieaO",
            "data": {
                "attack": {
                    "value": ""
                },
                "attackEffects": {
                    "value": []
                },
                "bonus": {
                    "value": 35
                },
                "damageRolls": {
                    "w12r1w4a5x86pxq3l35s": {
                        "damage": "4d4+13",
                        "damageType": "slashing"
                    }
                },
                "description": {
                    "value": ""
                },
                "rules": [],
                "slug": null,
                "source": {
                    "value": ""
                },
                "traits": {
                    "custom": "",
                    "rarity": {
                        "value": "common"
                    },
                    "value": [
                        "agile",
                        "disarm",
                        "finesse",
                        "magical",
                        "parry",
                        "twin"
                    ]
                },
                "weaponType": {
                    "value": "melee"
                }
            },
            "effects": [],
            "flags": {},
            "img": "systems/pf2e/icons/default-icons/melee.svg",
            "name": "Butterfly Sword",
            "sort": 400000,
            "type": "melee"
        },
        {
            "_id": "Se53bpbLQVBavu5z",
            "data": {
                "actionCategory": {
                    "value": "interaction"
                },
                "actionType": {
                    "value": "action"
                },
                "actions": {
                    "value": "1"
                },
                "description": {
                    "value": "<p>Nai Yan Fei adopts a mundane disguise, appearing as a nondescript human with a neutral alignment and a mundane occupation such as common laborer, farmer, or peasant. She can return to her typical persona as empress at any time by using Quick Change again.</p>"
                },
                "requirements": {
                    "value": ""
                },
                "rules": [],
                "slug": null,
                "source": {
                    "value": ""
                },
                "traits": {
                    "custom": "",
                    "rarity": {
                        "value": "common"
                    },
                    "value": []
                },
                "trigger": {
                    "value": ""
                },
                "weapon": {
                    "value": ""
                }
            },
            "effects": [],
            "flags": {},
            "img": "systems/pf2e/icons/actions/OneAction.webp",
            "name": "Quick Change",
            "sort": 500000,
            "type": "action"
        },
        {
            "_id": "AJWBrF8k93sPpCiT",
            "data": {
                "actionCategory": {
                    "value": "offensive"
                },
                "actionType": {
                    "value": "free"
                },
                "actions": {
                    "value": ""
                },
                "description": {
                    "value": "<p><strong>Trigger</strong> Nai Yan Fei hits a flat-footed creature and deals damage.</p>\n<p><strong>Effect</strong> Nai Yan Fei applies one of the following debilitations, which lasts until the end of her next turn.</p>\n<p>• <strong>Debilitation</strong> The target takes a –10-foot status penalty to its Speeds.</p>\n<p>• <strong>Debilitation</strong> The target becomes @Compendium[pf2e.conditionitems.Enfeebled]{Enfeebled 1}.</p>\n<p>• <strong>Debilitation</strong> The target can’t flank other creatures, and it can’t provide flanking for its allies.</p>\n<p>•</p>\n<p><strong>Debilitation</strong> The target doesn’t gain a circumstance bonus to AC from Raising a Shield, lesser cover, or standard cover; it gains only a +2 circumstance bonus to AC from greater cover or Taking Cover.</p>"
                },
                "requirements": {
                    "value": ""
                },
                "rules": [],
                "slug": null,
                "source": {
                    "value": ""
                },
                "traits": {
                    "custom": "",
                    "rarity": {
                        "value": "common"
                    },
                    "value": []
                },
                "trigger": {
                    "value": ""
                },
                "weapon": {
                    "value": ""
                }
            },
            "effects": [],
            "flags": {},
            "img": "systems/pf2e/icons/actions/FreeAction.webp",
            "name": "Debilitating Strike",
            "sort": 600000,
            "type": "action"
        },
        {
            "_id": "NCYjm0t24Miq4JkP",
            "data": {
                "actionCategory": {
                    "value": "offensive"
                },
                "actionType": {
                    "value": "reaction"
                },
                "actions": {
                    "value": ""
                },
                "description": {
                    "value": "<p><strong>Trigger</strong> Nai Yan Fei hits a flat-footed creature and deals damage.</p>\n<p><strong>Effect</strong> The target attempts a <span data-pf2-check=\"fortitude\" data-pf2-traits=\"incapacitation\" data-pf2-label=\"\" data-pf2-dc=\"39\" data-pf2-show-dc=\"gm\">Fortitude</span> save. It then becomes immune to Nai Yan Fei’s Master Strike for 1 day.</p>\n<hr />\n<p><strong>Critical Success</strong> The target is unaffected.</p>\n<p><strong>Success</strong> The target is @Compendium[pf2e.conditionitems.Enfeebled]{Enfeebled 2} until the end of Nai Yan Fei’s next turn.</p>\n<p><strong>Failure</strong> The target is @Compendium[pf2e.conditionitems.Paralyzed]{Paralyzed} for 4 rounds.</p>\n<p><strong>Critical Failure</strong> The target is @Compendium[pf2e.conditionitems.Paralyzed]{Paralyzed} for 4 rounds, knocked @Compendium[pf2e.conditionitems.Unconscious]{Unconscious} for 2 hours, or killed (Nai Yan Fei’s choice).</p>"
                },
                "requirements": {
                    "value": ""
                },
                "rules": [],
                "slug": null,
                "source": {
                    "value": ""
                },
                "traits": {
                    "custom": "",
                    "rarity": {
                        "value": "common"
                    },
                    "value": [
                        "incapacitation"
                    ]
                },
                "trigger": {
                    "value": ""
                },
                "weapon": {
                    "value": ""
                }
            },
            "effects": [],
            "flags": {},
            "img": "systems/pf2e/icons/actions/Reaction.webp",
            "name": "Master Strike",
            "sort": 700000,
            "type": "action"
        },
        {
            "_id": "lIRKupSMCC2L13AH",
            "data": {
                "actionCategory": {
                    "value": "offensive"
                },
                "actionType": {
                    "value": "passive"
                },
                "actions": {
                    "value": ""
                },
                "description": {
                    "value": "<p>When the monster Strikes a creature that has the @Compendium[pf2e.conditionitems.Flat-Footed]{Flat-Footed} condition with an agile or finesse melee weapon, an agile or finesse unarmed attack, or a ranged weapon attack, it also deals the listed precision damage. For a ranged attack with a thrown weapon, that weapon must also be an agile or finesse weapon.</p>\n<p>Nai Yan Fei's Strikes deal an additional [[/r 4d6 #precision]]{4d6 precision damage} to flat-footed creatures.</p>"
                },
                "requirements": {
                    "value": ""
                },
                "rules": [
                    {
                        "category": "precision",
                        "diceNumber": 4,
                        "dieSize": "d6",
                        "key": "PF2E.RuleElement.DamageDice",
                        "predicate": {
                            "all": [
                                "target:flatFooted"
                            ],
                            "any": [
                                "finesse",
                                "agile",
                                "ranged"
                            ]
                        },
                        "selector": "damage"
                    }
                ],
                "slug": "sneak-attack",
                "source": {
                    "value": ""
                },
                "traits": {
                    "custom": "",
                    "rarity": {
                        "value": "common"
                    },
                    "value": []
                },
                "trigger": {
                    "value": ""
                },
                "weapon": {
                    "value": ""
                }
            },
            "effects": [],
            "flags": {
                "core": {
                    "sourceId": "Compendium.pf2e.bestiary-ability-glossary-srd.AWvNPE4U0kEJSL1T"
                }
            },
            "img": "systems/pf2e/icons/actions/Passive.webp",
            "name": "Sneak Attack",
            "sort": 800000,
            "type": "action"
        },
        {
            "_id": "E43VMv7qY1wV53Md",
            "data": {
                "description": {
                    "value": ""
                },
                "mod": {
                    "value": 37
                },
                "proficient": {
                    "value": 0
                },
                "rules": [],
                "slug": null,
                "source": {
                    "value": ""
                },
                "traits": {
                    "custom": "",
                    "rarity": {
                        "value": "common"
                    },
                    "value": []
                }
            },
            "effects": [],
            "flags": {},
            "img": "systems/pf2e/icons/default-icons/lore.svg",
            "name": "Acrobatics",
            "sort": 900000,
            "type": "lore"
        },
        {
            "_id": "be4ZKhxOA4WEMVt2",
            "data": {
                "description": {
                    "value": ""
                },
                "mod": {
                    "value": 36
                },
                "proficient": {
                    "value": 0
                },
                "rules": [],
                "slug": null,
                "source": {
                    "value": ""
                },
                "traits": {
                    "custom": "",
                    "rarity": {
                        "value": "common"
                    },
                    "value": []
                }
            },
            "effects": [],
            "flags": {},
            "img": "systems/pf2e/icons/default-icons/lore.svg",
            "name": "Arcana",
            "sort": 1000000,
            "type": "lore"
        },
        {
            "_id": "uSRvhqpB1Hs9dQTF",
            "data": {
                "description": {
                    "value": ""
                },
                "mod": {
                    "value": 36
                },
                "proficient": {
                    "value": 0
                },
                "rules": [],
                "slug": null,
                "source": {
                    "value": ""
                },
                "traits": {
                    "custom": "",
                    "rarity": {
                        "value": "common"
                    },
                    "value": []
                }
            },
            "effects": [],
            "flags": {},
            "img": "systems/pf2e/icons/default-icons/lore.svg",
            "name": "Deception",
            "sort": 1100000,
            "type": "lore"
        },
        {
            "_id": "lJ8PMqR4TeRBezaZ",
            "data": {
                "description": {
                    "value": ""
                },
                "mod": {
                    "value": 38
                },
                "proficient": {
                    "value": 0
                },
                "rules": [],
                "slug": null,
                "source": {
                    "value": ""
                },
                "traits": {
                    "custom": "",
                    "rarity": {
                        "value": "common"
                    },
                    "value": []
                }
            },
            "effects": [],
            "flags": {},
            "img": "systems/pf2e/icons/default-icons/lore.svg",
            "name": "Diplomacy",
            "sort": 1200000,
            "type": "lore"
        },
        {
            "_id": "VqlmcA8mbwRPwWPj",
            "data": {
                "description": {
                    "value": ""
                },
                "mod": {
                    "value": 38
                },
                "proficient": {
                    "value": 0
                },
                "rules": [],
                "slug": null,
                "source": {
                    "value": ""
                },
                "traits": {
                    "custom": "",
                    "rarity": {
                        "value": "common"
                    },
                    "value": []
                }
            },
            "effects": [],
            "flags": {},
            "img": "systems/pf2e/icons/default-icons/lore.svg",
            "name": "Goka Lore",
            "sort": 1300000,
            "type": "lore"
        },
        {
            "_id": "s9A6uTcikvAORuxv",
            "data": {
                "description": {
                    "value": ""
                },
                "mod": {
                    "value": 36
                },
                "proficient": {
                    "value": 0
                },
                "rules": [],
                "slug": null,
                "source": {
                    "value": ""
                },
                "traits": {
                    "custom": "",
                    "rarity": {
                        "value": "common"
                    },
                    "value": []
                }
            },
            "effects": [],
            "flags": {},
            "img": "systems/pf2e/icons/default-icons/lore.svg",
            "name": "Intimidation",
            "sort": 1400000,
            "type": "lore"
        },
        {
            "_id": "wohEWLl2eVsMhxnM",
            "data": {
                "description": {
                    "value": ""
                },
                "mod": {
                    "value": 38
                },
                "proficient": {
                    "value": 0
                },
                "rules": [],
                "slug": null,
                "source": {
                    "value": ""
                },
                "traits": {
                    "custom": "",
                    "rarity": {
                        "value": "common"
                    },
                    "value": []
                }
            },
            "effects": [],
            "flags": {},
            "img": "systems/pf2e/icons/default-icons/lore.svg",
            "name": "Legal Lore",
            "sort": 1500000,
            "type": "lore"
        },
        {
            "_id": "p0kLk0IQA7DniZv7",
            "data": {
                "description": {
                    "value": ""
                },
                "mod": {
                    "value": 38
                },
                "proficient": {
                    "value": 0
                },
                "rules": [],
                "slug": null,
                "source": {
                    "value": ""
                },
                "traits": {
                    "custom": "",
                    "rarity": {
                        "value": "common"
                    },
                    "value": []
                }
            },
            "effects": [],
            "flags": {},
            "img": "systems/pf2e/icons/default-icons/lore.svg",
            "name": "Occultism",
            "sort": 1600000,
            "type": "lore"
        },
        {
            "_id": "IZMP8cvNrBXMr9tN",
            "data": {
                "description": {
                    "value": ""
                },
                "mod": {
                    "value": 36
                },
                "proficient": {
                    "value": 0
                },
                "rules": [],
                "slug": null,
                "source": {
                    "value": ""
                },
                "traits": {
                    "custom": "",
                    "rarity": {
                        "value": "common"
                    },
                    "value": []
                }
            },
            "effects": [],
            "flags": {},
            "img": "systems/pf2e/icons/default-icons/lore.svg",
            "name": "Performance",
            "sort": 1700000,
            "type": "lore"
        },
        {
            "_id": "aGCyyH5IJDUXZU0Q",
            "data": {
                "description": {
                    "value": ""
                },
                "mod": {
                    "value": 32
                },
                "proficient": {
                    "value": 0
                },
                "rules": [],
                "slug": null,
                "source": {
                    "value": ""
                },
                "traits": {
                    "custom": "",
                    "rarity": {
                        "value": "common"
                    },
                    "value": []
                }
            },
            "effects": [],
            "flags": {},
            "img": "systems/pf2e/icons/default-icons/lore.svg",
            "name": "Religion",
            "sort": 1800000,
            "type": "lore"
        },
        {
            "_id": "oBz12CaI29wI0U8K",
            "data": {
                "description": {
                    "value": ""
                },
                "mod": {
                    "value": 38
                },
                "proficient": {
                    "value": 0
                },
                "rules": [],
                "slug": null,
                "source": {
                    "value": ""
                },
                "traits": {
                    "custom": "",
                    "rarity": {
                        "value": "common"
                    },
                    "value": []
                }
            },
            "effects": [],
            "flags": {},
            "img": "systems/pf2e/icons/default-icons/lore.svg",
            "name": "Society",
            "sort": 1900000,
            "type": "lore"
        },
        {
            "_id": "EhJ41OaBTYrxKITt",
            "data": {
                "description": {
                    "value": ""
                },
                "mod": {
                    "value": 35
                },
                "proficient": {
                    "value": 0
                },
                "rules": [],
                "slug": null,
                "source": {
                    "value": ""
                },
                "traits": {
                    "custom": "",
                    "rarity": {
                        "value": "common"
                    },
                    "value": []
                }
            },
            "effects": [],
            "flags": {},
            "img": "systems/pf2e/icons/default-icons/lore.svg",
            "name": "Stealth",
            "sort": 2000000,
            "type": "lore"
        },
        {
            "_id": "NAjQ9JTOro54EWE3",
            "data": {
                "description": {
                    "value": ""
                },
                "mod": {
                    "value": 35
                },
                "proficient": {
                    "value": 0
                },
                "rules": [],
                "slug": null,
                "source": {
                    "value": ""
                },
                "traits": {
                    "custom": "",
                    "rarity": {
                        "value": "common"
                    },
                    "value": []
                }
            },
            "effects": [],
            "flags": {},
            "img": "systems/pf2e/icons/default-icons/lore.svg",
            "name": "Thievery",
            "sort": 2100000,
            "type": "lore"
        },
        {
            "_id": "NQj5efGU5Hd9oMP3",
            "data": {
                "description": {
                    "value": ""
                },
                "mod": {
                    "value": 36
                },
                "proficient": {
                    "value": 0
                },
                "rules": [],
                "slug": null,
                "source": {
                    "value": ""
                },
                "traits": {
                    "custom": "",
                    "rarity": {
                        "value": "common"
                    },
                    "value": []
                }
            },
            "effects": [],
            "flags": {},
            "img": "systems/pf2e/icons/default-icons/lore.svg",
            "name": "Underworld Lore",
            "sort": 2200000,
            "type": "lore"
        }
    ],
    "name": "Nai Yan Fei",
    "token": {
        "disposition": -1,
        "height": 1,
        "img": "systems/pf2e/icons/default-icons/npc.svg",
        "name": "Nai Yan Fei",
        "width": 1
    },
    "type": "npc"
}
