{
    "_id": "AqslI71DReZOzgAW",
    "img": "systems/pf2e/icons/equipment/consumables/oils/oil-of-revelation.webp",
    "name": "Formulated Sunlight",
    "system": {
        "baseItem": null,
        "bulk": {
            "value": 0.1
        },
        "category": "other",
        "containerId": null,
        "damage": null,
        "description": {
            "value": "<p>A leshy can derive nourishment from specially formulated bottles of sunlight instead of natural sunlight.</p>"
        },
        "hardness": 0,
        "hp": {
            "max": 0,
            "value": 0
        },
        "level": {
            "value": 0
        },
        "material": {
            "grade": null,
            "type": null
        },
        "price": {
            "value": {
                "sp": 40
            }
        },
        "publication": {
            "license": "OGL",
            "remaster": false,
            "title": "Pathfinder Lost Omens: Character Guide"
        },
        "quantity": 1,
        "rules": [],
        "size": "med",
        "traits": {
            "rarity": "common",
            "value": [
                "consumable"
            ]
        },
        "usage": {
            "value": "held-in-one-hand"
        },
        "uses": {
            "autoDestroy": true,
            "max": 7,
            "value": 7
        }
    },
    "type": "consumable"
}
